{"trial_id": "02", "hyperparameters": {"space": [{"class_name": "Choice", "config": {"name": "n_layers", "default": 2, "conditions": [], "values": [2, 3], "ordered": true}}, {"class_name": "Choice", "config": {"name": "units_0", "default": 64, "conditions": [], "values": [64, 128], "ordered": true}}, {"class_name": "Choice", "config": {"name": "activation_0", "default": "relu", "conditions": [], "values": ["relu", "tanh"], "ordered": false}}, {"class_name": "Choice", "config": {"name": "units_1", "default": 64, "conditions": [], "values": [64, 128], "ordered": true}}, {"class_name": "Choice", "config": {"name": "activation_1", "default": "relu", "conditions": [], "values": ["relu", "tanh"], "ordered": false}}, {"class_name": "Choice", "config": {"name": "units_2", "default": 64, "conditions": [], "values": [64, 128], "ordered": true}}, {"class_name": "Choice", "config": {"name": "activation_2", "default": "relu", "conditions": [], "values": ["relu", "tanh"], "ordered": false}}], "values": {"n_layers": 3, "units_0": 64, "activation_0": "tanh", "units_1": 128, "activation_1": "tanh", "units_2": 128, "activation_2": "tanh"}}, "metrics": {"metrics": {}}, "score": null, "best_step": 0, "status": "RUNNING", "message": null}